{
  "issue": {
    "identifier": "TXMO-ISSUE-199501",
    "publication": "Texas Monthly",
    "issue": "January 1995",
    "pdf_uri": "/1995/19950100.pdf",
    "month": "January",
    "year": 1995,
    "pages": 204,
    "document_toc_page": "5"
  },
  "toc": [
    {
      "heading": "Texas Monthly",
      "section": [
        {
          "section_heading": "Departments",
          "toc_entry": [
            {
              "title": "Critter Bidders",
              "subtitle": "Business",
              "description": "",
              "byline": "by Anne Dingus",
              "page": "30"
            },
            {
              "title": "Big Talker",
              "subtitle": "Politics",
              "description": "",
              "byline": "by Glenna Whitley",
              "page": "36"
            },
            {
              "title": "Latin Bear",
              "subtitle": "Travel",
              "description": "",
              "byline": "by Joe Nick Patoski",
              "page": "48"
            },
            {
              "title": "Fast and Loose",
              "subtitle": "Music",
              "description": "",
              "byline": "by John Morthland",
              "page": "87"
            }
          ]
        },
        {
          "section_heading": "Miscellany",
          "toc_entry": [
            {
              "title": "The Gate-Crashers",
              "subtitle": "Behind the Lines",
              "description": "",
              "byline": "by Gregory Curtis",
              "page": "5"
            },
            {
              "title": "Roar off the Crowd",
              "subtitle": "",
              "description": "",
              "byline": "",
              "page": "12"
            },
            {
              "title": "Around the State",
              "subtitle": "",
              "description": "",
              "byline": "",
              "page": "16"
            },
            {
              "title": "State Wide Reporter",
              "subtitle": "",
              "description": "",
              "byline": "Edited by David McCormick",
              "page": "90"
            },
            {
              "title": "State off the Art",
              "subtitle": "",
              "description": "",
              "byline": "",
              "page": "105"
            },
            {
              "title": "State Fare",
              "subtitle": "",
              "description": "",
              "byline": "",
              "page": "167"
            },
            {
              "title": "Restaurant Guide",
              "subtitle": "",
              "description": "",
              "byline": "",
              "page": "169"
            },
            {
              "title": "State Secrets",
              "subtitle": "",
              "description": "",
              "byline": "by Paul Burka",
              "page": "200"
            }
          ]
        },
        {
          "section_heading": "Features",
          "toc_entry": [
            {
              "title": "The 1995 Bum Steer Awards",
              "subtitle": "",
              "description": "A year of amorous angels, bra buzzers, camouflaged Claytie, denied Davidians, escaped evangelists, faulty flags, gainful gangs, hefty hypnosis, inmate inedibles, jumbo jockstraps, kaput killdeers, lunching Lassie, mercurial mushrooms, nabbed ninjas, overhyped O.J., pumpkin purloiners, questionable quizzes, rap ruffians, sexy sprinters, tacky taxis, unappreciated universities, videotaped villains, wayward Willie, X-sposing X-ministers, yammering Yankees, and zero zippers.",
              "byline": "",
              "page": "106"
            },
            {
              "title": "Is Mcc Obsolete?",
              "subtitle": "",
              "description": "Twelve years and hundreds of millions of dollars later, the vaunted Austin high-tech consortium is still struggling to find its purpose.",
              "byline": "by Helen Thorpe",
              "page": "118"
            },
            {
              "title": "Breaking the Bank",
              "subtitle": "",
              "description": "Gambling became a way of life for young Josh Levine. When he got in too deep, he came to believe that only a holdup could get him out.",
              "byline": "by Alex Hecht",
              "page": "122",
              "wp_post_id": "129813",
              "identifier": "txmo-article-199501-breakingt.json"
            },
            {
              "title": "Barry Switzer Gets The Last Laugh",
              "subtitle": "",
              "description": "The rookie Cowboys coach has turned out to be exactly what all the critics said he wasn’t: a winner.",
              "byline": "by Bud Shrake",
              "page": "126",
              "wp_post_id": "129807",
              "identifier": "txmo-article-199501-barryswit.json"
            },
            {
              "title": "Brush With Fame",
              "subtitle": "",
              "description": "As a curator and in his own work as a painter, Jerry Bywaters left a lasting legacy of Texas art.",
              "byline": "by Anne Dingus",
              "page": "128"
            },
            {
              "title": "Closing the Circle J",
              "subtitle": "",
              "description": "A final farewell to the Hill Country spread that for more than thirty years meant everything to me and my family.",
              "byline": "by Robert Draper",
              "page": "132"
            }
          ]
        }
      ]
    }
  ]
}